{
  "_class": "shapeGroup",
  "booleanOperation": 0,
  "clippingMaskMode": 0,
  "do_objectID": "AF17F6FC-DA0F-4A15-8CE9-69BB27E416DB",
  "exportOptions": {
    "_class": "exportOptions",
    "do_objectID": "E6B2BF6A-2467-435E-8AE7-0EA1AD7E2B08",
    "exportFormats": [
    ],
    "includedLayerIds": [
    ],
    "layerOptions": 0,
    "shouldTrim": false
  },
  "frame": {
    "_class": "rect",
    "constrainProportions": false,
    "do_objectID": "A183406D-C97E-4E90-9F60-6238FE517ABE",
    "height": 17.37510040160644,
    "width": 5.035652815342992,
    "x": 33.57101876895336,
    "y": 8.019277108433739
  },
  "groupLayout": {
    "_class": "MSImmutableFreeformGroupLayout"
  },
  "hasClickThrough": false,
  "hasClippingMask": false,
  "isFixedToViewport": false,
  "isFlippedHorizontal": false,
  "isFlippedVertical": false,
  "isLocked": false,
  "isVisible": true,
  "layerListExpandedType": 1,
  "layers": [
    {
      "class": "shapePath",
      "id": "5C676508-3FD4-468F-96EA-5BA2C8B7F6D5"
    },
    {
      "class": "shapePath",
      "id": "72471D28-A7BF-4A57-BFCA-89A965D6F52D"
    },
    {
      "class": "shapePath",
      "id": "01A2FA5A-9C72-43C8-BFD3-F835E4DB1F75"
    }
  ],
  "name": "Fill 25",
  "nameIsFixed": false,
  "resizingConstraint": 63,
  "resizingType": 0,
  "rotation": 0,
  "shouldBreakMaskChain": false,
  "style": {
    "_class": "style",
    "do_objectID": "D54232B4-1720-49A7-84F6-518C6BE1D6FB",
    "endMarkerType": 0,
    "fills": [
      {
        "_class": "fill",
        "color": {
          "_class": "color",
          "alpha": 1,
          "blue": 0.129,
          "green": 0.635,
          "red": 0.976
        },
        "fillType": 0,
        "isEnabled": true,
        "noiseIndex": 0,
        "noiseIntensity": 0,
        "patternFillType": 1,
        "patternTileScale": 1
      }
    ],
    "miterLimit": 10,
    "startMarkerType": 0,
    "windingRule": 1
  },
  "windingRule": 1
}