{
  "_class": "rectangle",
  "booleanOperation": -1,
  "clippingMaskMode": 0,
  "do_objectID": "48CE7F04-9DBB-4598-B7EE-3BC6E1506F27",
  "edited": false,
  "exportOptions": {
    "_class": "exportOptions",
    "do_objectID": "7602764E-6869-415A-85FB-F2DFC5782754",
    "exportFormats": [
    ],
    "includedLayerIds": [
    ],
    "layerOptions": 0,
    "shouldTrim": false
  },
  "fixedRadius": 0,
  "frame": {
    "_class": "rect",
    "constrainProportions": false,
    "do_objectID": "A99D8474-4308-4CAC-BBCB-6EA964DB02A6",
    "height": 2,
    "width": 505.7500000000011,
    "x": 0,
    "y": 0
  },
  "hasClippingMask": false,
  "hasConvertedToNewRoundCorners": true,
  "isClosed": true,
  "isFixedToViewport": false,
  "isFlippedHorizontal": false,
  "isFlippedVertical": false,
  "isLocked": false,
  "isVisible": true,
  "layerListExpandedType": 1,
  "name": "hr",
  "nameIsFixed": true,
  "pointRadiusBehaviour": 0,
  "points": [
    {
      "_class": "curvePoint",
      "cornerRadius": 0,
      "curveFrom": "{0, 0}",
      "curveMode": 1,
      "curveTo": "{0, 0}",
      "hasCurveFrom": false,
      "hasCurveTo": false,
      "point": "{0, 0}"
    },
    {
      "_class": "curvePoint",
      "cornerRadius": 0,
      "curveFrom": "{0.99999999999999989, 0}",
      "curveMode": 1,
      "curveTo": "{0.99999999999999989, 0}",
      "hasCurveFrom": false,
      "hasCurveTo": false,
      "point": "{0.99999999999999989, 0}"
    },
    {
      "_class": "curvePoint",
      "cornerRadius": 0,
      "curveFrom": "{0.99999999999999989, 1.0000000000000002}",
      "curveMode": 1,
      "curveTo": "{0.99999999999999989, 1.0000000000000002}",
      "hasCurveFrom": false,
      "hasCurveTo": false,
      "point": "{0.99999999999999989, 1.0000000000000002}"
    },
    {
      "_class": "curvePoint",
      "cornerRadius": 0,
      "curveFrom": "{0, 1.0000000000000002}",
      "curveMode": 1,
      "curveTo": "{0, 1.0000000000000002}",
      "hasCurveFrom": false,
      "hasCurveTo": false,
      "point": "{0, 1.0000000000000002}"
    }
  ],
  "resizingConstraint": 63,
  "resizingType": 0,
  "rotation": 0,
  "sharedStyleID": "25E79BF1-2766-4CC1-B2CB-5B0F5721F6C3",
  "shouldBreakMaskChain": false,
  "style": {
    "_class": "style",
    "blur": {
      "_class": "blur",
      "center": "{0.5, 0.5}",
      "do_objectID": "1DCC51D1-C35C-4765-9FD2-DCBC17870F7C",
      "isEnabled": false,
      "motionAngle": 0,
      "radius": 8.33333741764182,
      "saturation": 1,
      "type": 0
    },
    "do_objectID": "CC6C587E-4063-4064-84EA-D28288E9A0C7",
    "endMarkerType": 0,
    "fills": [
      {
        "_class": "fill",
        "color": {
          "_class": "color",
          "alpha": 1,
          "blue": 0.6,
          "green": 0.6,
          "red": 0.6
        },
        "fillType": 0,
        "isEnabled": true,
        "noiseIndex": 0,
        "noiseIntensity": 0,
        "patternFillType": 0,
        "patternTileScale": 1
      }
    ],
    "miterLimit": 10,
    "startMarkerType": 0,
    "windingRule": 1
  },
  "userInfo": {
    "com.animaapp.stc-sketch-plugin": {
      "kModelPropertiesKey": {
      }
    }
  }
}