{
  "_class": "rectangle",
  "booleanOperation": -1,
  "clippingMaskMode": 0,
  "do_objectID": "653E9208-7B5F-4C6E-A42B-5C2146AA37C3",
  "edited": false,
  "exportOptions": {
    "_class": "exportOptions",
    "do_objectID": "624687C4-289B-47F7-86F2-8E6987C7B684",
    "exportFormats": [
    ],
    "includedLayerIds": [
    ],
    "layerOptions": 0,
    "shouldTrim": false
  },
  "fixedRadius": 0,
  "frame": {
    "_class": "rect",
    "constrainProportions": false,
    "do_objectID": "C5311DF5-C95C-48AC-9789-9AED91BA3A3F",
    "height": 125,
    "width": 381,
    "x": 0,
    "y": 0
  },
  "hasClippingMask": false,
  "hasConvertedToNewRoundCorners": true,
  "isClosed": true,
  "isFixedToViewport": false,
  "isFlippedHorizontal": false,
  "isFlippedVertical": false,
  "isLocked": false,
  "isVisible": true,
  "layerListExpandedType": 1,
  "name": "container",
  "nameIsFixed": true,
  "pointRadiusBehaviour": 0,
  "points": [
    {
      "_class": "curvePoint",
      "cornerRadius": 0,
      "curveFrom": "{0, 0}",
      "curveMode": 1,
      "curveTo": "{0, 0}",
      "hasCurveFrom": false,
      "hasCurveTo": false,
      "point": "{0, 0}"
    },
    {
      "_class": "curvePoint",
      "cornerRadius": 0,
      "curveFrom": "{1.000000000000002, 0}",
      "curveMode": 1,
      "curveTo": "{1.000000000000002, 0}",
      "hasCurveFrom": false,
      "hasCurveTo": false,
      "point": "{1.000000000000002, 0}"
    },
    {
      "_class": "curvePoint",
      "cornerRadius": 0,
      "curveFrom": "{1.000000000000002, 1}",
      "curveMode": 1,
      "curveTo": "{1.000000000000002, 1}",
      "hasCurveFrom": false,
      "hasCurveTo": false,
      "point": "{1.000000000000002, 1}"
    },
    {
      "_class": "curvePoint",
      "cornerRadius": 0,
      "curveFrom": "{0, 1}",
      "curveMode": 1,
      "curveTo": "{0, 1}",
      "hasCurveFrom": false,
      "hasCurveTo": false,
      "point": "{0, 1}"
    }
  ],
  "resizingConstraint": 63,
  "resizingType": 0,
  "rotation": 0,
  "shouldBreakMaskChain": false,
  "style": {
    "_class": "style",
    "do_objectID": "C6437A8C-A4AC-4970-AE91-ADC97BCC04BE",
    "endMarkerType": 0,
    "miterLimit": 10,
    "startMarkerType": 0,
    "windingRule": 1
  },
  "userInfo": {
    "com.animaapp.stc-sketch-plugin": {
      "kModelPropertiesKey": {
      }
    }
  }
}